{
  "indexes": [
    {
      "collectionGroup": "projects",
      "queryScope": "COLLECTION",
      "fields": [
        {
          "fieldPath": "uid",
          "order": "ASCENDING"
        },
        {
          "fieldPath": "order",
          "order": "ASCENDING"
        }
      ]
    },
    {
      "collectionGroup": "tasks",
      "queryScope": "COLLECTION",
      "fields": [
        {
          "fieldPath": "projectId",
          "order": "ASCENDING"
        },
        {
          "fieldPath": "priority",
          "order": "ASCENDING"
        }
      ]
    }
  ],
  "fieldOverrides": []
}
